MANIFEST.in
README.md
logo.png
setup.py
heteromotility/__init__.py
heteromotility/command_line.py
heteromotility/dfa.py
heteromotility/heteromotility.py
heteromotility/hmdetail.py
heteromotility/hmio.py
heteromotility/hmplot.py
heteromotility/hmsims.py
heteromotility/hmstats.py
heteromotility/hmtests.py
heteromotility/hmtools.py
heteromotility/hmtrack.py
heteromotility.egg-info/PKG-INFO
heteromotility.egg-info/SOURCES.txt
heteromotility.egg-info/dependency_links.txt
heteromotility.egg-info/entry_points.txt
heteromotility.egg-info/not-zip-safe
heteromotility.egg-info/requires.txt
heteromotility.egg-info/top_level.txt