Metadata-Version: 1.0
Name: heteromotility
Version: 0.1.8
Summary: Quantitative analysis of biological motion
Home-page: http://github.com/jacobkimmel/heteromotility
Author: Jacob Kimmel
Author-email: jacobkimmel@gmail.com
License: MIT
Platform: UNKNOWN
